django_global_search/__init__.py
django_global_search/admin.py
django_global_search/apps.py
django_global_search/permissions.py
django_global_search/searcher.py
django_global_search/settings.py
django_global_search/views.py
django_global_search/locale/ko/LC_MESSAGES/django.mo
django_global_search/locale/ko/LC_MESSAGES/django.po
django_global_search/static/django_global_search/css/global_search.css
django_global_search/static/django_global_search/js/global_search.js
django_global_search/templates/global_search/button.html
django_global_search/templates/global_search/search.html
django_global_search/templates/global_search/sidebar.html
django_global_search-0.1.2.dist-info/METADATA
django_global_search-0.1.2.dist-info/WHEEL
django_global_search-0.1.2.dist-info/licenses/LICENSE
django_global_search-0.1.2.dist-info/RECORD
