Metadata-Version: 2.4
Name: django-global-search
Version: 0.1.2
Summary: Global search for Django Admin, search across all registered models with permissions and search_fields support
Project-URL: Homepage, https://github.com/2ykwang/django-global-search
Project-URL: Repository, https://github.com/2ykwang/django-global-search
Project-URL: Documentation, https://django-global-search.readthedocs.io/en/latest/
Project-URL: Issues, https://github.com/2ykwang/django-global-search/issues
Author-email: Youngkwang Yang <me@youngkwang.dev>
License: MIT
License-File: LICENSE
Keywords: admin,django,global,search
Classifier: Framework :: Django
Classifier: Framework :: Django :: 4.2
Classifier: Framework :: Django :: 5.0
Classifier: Framework :: Django :: 5.1
Classifier: Framework :: Django :: 5.2
Classifier: License :: OSI Approved :: MIT License
Classifier: Programming Language :: Python :: 3
Classifier: Programming Language :: Python :: 3.9
Classifier: Programming Language :: Python :: 3.10
Classifier: Programming Language :: Python :: 3.11
Classifier: Programming Language :: Python :: 3.12
Classifier: Programming Language :: Python :: 3.13
Requires-Python: >=3.9
Requires-Dist: django>=4.2
